typehintenv/__init__.py
typehintenv/load.py
typehintenv/converters/__init__.py
typehintenv/converters/basic_types.py
typehintenv-0.2.0.dist-info/METADATA
typehintenv-0.2.0.dist-info/WHEEL
typehintenv-0.2.0.dist-info/RECORD
